bbdb/__init__.py
bbdb/bbdb.lark
bbdb/database.py
bbdb/model.py
bbdb/parser.py
bbdb/timestamp.py
pybbdb-0.7.dist-info/COPYING
pybbdb-0.7.dist-info/METADATA
pybbdb-0.7.dist-info/WHEEL
pybbdb-0.7.dist-info/top_level.txt
pybbdb-0.7.dist-info/RECORD
