Metadata-Version: 2.1
Name: pybbdb
Version: 0.7
Summary: Interface to BBDB, the Insidious Big Brother Database
Home-page: https://sr.ht/~zondo/pybbdb
Author: Glenn Hutchings
Author-email: zondo42@gmail.com
License: GPL v2 or later
Platform: UNKNOWN
Classifier: Development Status :: 4 - Beta
Classifier: Environment :: Console
Classifier: Intended Audience :: Developers
Classifier: License :: OSI Approved :: GNU General Public License v2 or later (GPLv2+)
Classifier: Natural Language :: English
Classifier: Operating System :: Microsoft :: Windows
Classifier: Operating System :: POSIX :: Linux
Classifier: Operating System :: Unix
Classifier: Programming Language :: Python :: 3
Classifier: Topic :: Communications :: Email :: Address Book
Classifier: Topic :: Database
Requires-Dist: lark
Requires-Dist: pydantic
Requires-Dist: python-dateutil
